russborrow/.DS_Store
russborrow/README.md
russborrow/__init__.py
russborrow/borrowed_dictionary.csv
russborrow/main.py
russborrow-0.0.7.dist-info/METADATA
russborrow-0.0.7.dist-info/WHEEL
russborrow-0.0.7.dist-info/RECORD
